ALU.v
module ALU (output reg[7:0] reg_out, output reg[3:0] SREG, input[3:0] function_select_lines, input[7:0] operandA, input[7:0] operandB, input clk);
    wire signed[7:0] operandA, operandB;

    always @ (posedge clk, operandA, operandB, function_select_lines) begin
        case(function_select_lines)
            4'b0000: begin
                         SREG <= 4'b0000;
                         reg_out <= reg_out;
                     end
            4'b0001: begin
                         {SREG[1], reg_out} = operandA+operandB;
                         SREG[0] = (reg_out === 0)?1:0;
                         SREG[2] = reg_out[7];
                         SREG[3] = (~reg_out[7]&operandA[7]&operandB[7]) | (reg_out[7]&~operandA[7]&~operandB[7]);
                     end
            4'b0010: begin
                         {SREG[1], reg_out} = operandA-operandB;
                         SREG[0] = (reg_out === 0)?1:0;
                         SREG[2] = reg_out[7];
                         SREG[3] = (~reg_out[7]&operandA[7]&~operandB[7]) | (reg_out[7]&~operandA[7]&operandB[7]);
                     end
            4'b0011: begin
                         {SREG[1], reg_out} = operandA+operandB+SREG[1];
                         SREG[0] = (reg_out === 0)?1:0;
                         SREG[2] = reg_out[7];
                         SREG[3] = (~reg_out[7]&operandA[7]&operandB[7]) | (reg_out[7]&~operandA[7]&~operandB[7]);
                     end
            4'b0100: begin
                         {SREG[1], reg_out} <= operandA-operandB-SREG[1];
                         SREG[0] <= (reg_out === 0)?1:0;
                         SREG[2] <= reg_out[7];
                         SREG[3] <= (~reg_out[7]&operandA[7]&~operandB[7]) | (reg_out[7]&~operandA[7]&operandB[7]);
                     end
            4'b0101: begin
                         SREG[0] <= ({operandA[7], operandA} <= {operandB[7], operandB})?1:0;
                         SREG[1] <= 1'b0;
                         SREG[2] <= 1'b0;
                         SREG[3] <= 1'b0;
                     end
            4'b0110: begin
                         SREG[3:1] <= 3'b000;
                         reg_out = operandA|operandB;
                         SREG[0] = (reg_out === 0)?1:0;
                     end
            4'b0111: begin
                         SREG[3:1] <= 3'b000;
                         reg_out = operandA&operandB;
                         SREG[0] = (reg_out === 0)?1:0;
                     end
            default: begin
                         SREG <= 4'b0000;
                         reg_out <= reg_out;
                     end
        endcase
    end
endmodule

clock.v
`timescale 1ns/1ps

module clock #(parameter tickRate = 1) (output reg clk);
    initial begin
        clk = 1'b0;
        forever #tickRate clk = ~clk;
    end
endmodule

behavioral-model/ALU-test.v
module testbench;

    wire[3:0] SREG;
    wire[7:0] reg_out;
    reg[7:0] A, B;
    reg[3:0] function_select_lines;
    wire clk;

    initial begin
        $dumpfile("test-ALU-adder-sub.vcd");
        $dumpvars(0, testbench);
    end

    clock clok(clk);
    ALU uut (reg_out, SREG, function_select_lines, A, B, clk);

    initial begin
        #5 A = 6; B = 9; function_select_lines = 1;
        #5 A = 3; B = 6; function_select_lines = 2;
        #5 A = 127; B = 125; function_select_lines = 3;
        #5 A = 1; B = 2; function_select_lines = 4;
        #5 function_select_lines = 0;
        #5 A = 5; B = 5; function_select_lines = 5;
        #5 A = 13; B = 85; function_select_lines = 6;
        #5 function_select_lines = 7;
        #5 function_select_lines = 8;
        #5 $finish;
    end
endmodule

test-ALU-adder-sub.vcd
$date
	Fri Nov 29 13:38:16 2019
$end
$version
	Icarus Verilog
$end
$timescale
	1s
$end
$scope module testbench $end
$var wire 8 ! reg_out [7:0] $end
$var wire 1 " clk $end
$var wire 4 # SREG [3:0] $end
$var reg 8 $ A [7:0] $end
$var reg 8 % B [7:0] $end
$var reg 4 & function_select_lines [3:0] $end
$scope module clok $end
$var reg 1 " clk $end
$upscope $end
$scope module uut $end
$var wire 1 " clk $end
$var wire 4 ' function_select_lines [3:0] $end
$var wire 8 ( operandA [7:0] $end
$var wire 8 ) operandB [7:0] $end
$var reg 4 * SREG [3:0] $end
$var reg 8 + reg_out [7:0] $end
$upscope $end
$upscope $end
$enddefinitions $end
#0
$dumpvars
bx +
bx *
bx )
bx (
bx '
bx &
bx %
bx $
bx #
0"
bx !
$end
#1
b0 #
b0 *
1"
#2
0"
#3
1"
#4
0"
#5
b1111 !
b1111 +
1"
b1 &
b1 '
b1001 %
b1001 )
b110 $
b110 (
#6
0"
#7
1"
#8
0"
#9
1"
#10
b110 #
b110 *
b11111101 !
b11111101 +
0"
b10 &
b10 '
b110 %
b110 )
b11 $
b11 (
#11
1"
#12
0"
#13
1"
#14
0"
#15
b1100 #
b1100 *
1"
b11 &
b11 '
b1111101 %
b1111101 )
b1111111 $
b1111111 (
#16
0"
#17
b11111100 !
b11111100 +
1"
#18
0"
#19
1"
#20
b110 #
b110 *
b11111111 !
b11111111 +
0"
b100 &
b100 '
b10 %
b10 )
b1 $
b1 (
#21
b11111110 !
b11111110 +
1"
#22
0"
#23
1"
#24
0"
#25
b0 #
b0 *
1"
b0 &
b0 '
#26
0"
#27
1"
#28
0"
#29
1"
#30
b1 #
b1 *
0"
b101 &
b101 '
b101 %
b101 )
b101 $
b101 (
#31
1"
#32
0"
#33
1"
#34
0"
#35
b0 #
b0 *
b1011101 !
b1011101 +
1"
b110 &
b110 '
b1010101 %
b1010101 )
b1101 $
b1101 (
#36
0"
#37
1"
#38
0"
#39
1"
#40
b101 !
b101 +
0"
b111 &
b111 '
#41
1"
#42
0"
#43
1"
#44
0"
#45
1"
b1000 &
b1000 '
