ALU.v
module ALU (output reg[7:0] reg_out, output reg[3:0] SREG, input[3:0] function_select_lines, input[7:0] operandA, input[7:0] operandB);
    /*
    wire adderSubtractor_enable;
    wire increment_enable;
    wire comparator_enable;
    wire or_enable;
    wire and_enable;
    wire shifter_enable;
    wire not_enable;

    assign adderSubtractor_enable = (function_select_lines[3:1] == 3'b000)?1:0;
    assign incrementer_enable = (function_select_lines == 4'b0010)?1:0;
    assign comparator_enable = (function_select_lines == 4'b0011)?1:0;
    assign or_enable = (function_select_lines == 4'b0100)?1:0;
    assign and_enable = (function_select_lines == 4'b0101)?1:0;
    assign shifter_enable = (function_select_lines[3:1] == 3'b011)?1:0;
    assign not_enable = (function_select_lines == 4'b1000)?1:0;
    assign xor_enable = (function_select_lines == 4'b1001)?1:0;


    adderSubtractor8Bit adder_subtractor (SREG, reg_out, operandA, operandB, function_select_lines[0], adderSubtractor_enable);
    adderSubtractor8Bit incrementer (SREG, operandA, operandA, 8'b1, 1'b0, incrementer_enable);
    */
    always @ (function_select_lines, operandA, operandB) begin
        case(function_select_lines)
            4'b0000: begin
                         SREG <= 4'b0000;
                         reg_out <= reg_out;
                     end
            4'b0001: begin
                         {SREG[1], reg_out} = operandA+operandB;
                         SREG[0] = (reg_out === 0)?1:0;
                         SREG[2] = reg_out[7];
                         SREG[3] = (~reg_out[7]&operandA[7]&operandB[7]) | (reg_out[7]&~operandA[7]&~operandB[7]);
                     end
            4'b0010: begin
                         {SREG[1], reg_out} = operandA-operandB;
                         SREG[0] = (reg_out === 0)?1:0;
                         SREG[2] = reg_out[7];
                         SREG[3] = (~reg_out[7]&operandA[7]&~operandB[7]) | (reg_out[7]&~operandA[7]&operandB[7]);
                     end
            4'b0011: begin
                         {SREG[1], reg_out} = operandA+operandB+SREG[1];
                         SREG[0] = (reg_out === 0)?1:0;
                         SREG[2] = reg_out[7];
                         SREG[3] = (~reg_out[7]&operandA[7]&operandB[7]) | (reg_out[7]&~operandA[7]&~operandB[7]);
                     end
            4'b0100: begin
                         {SREG[1], reg_out} <= operandA-operandB-SREG[1];
                         SREG[0] <= (reg_out === 0)?1:0;
                         SREG[2] <= reg_out[7];
                         SREG[3] <= (~reg_out[7]&operandA[7]&~operandB[7]) | (reg_out[7]&~operandA[7]&operandB[7]);
                     end
            4'b0101: begin
                         SREG[0] <= (operandA <= operandB)?1:0;
                         SREG[1] <= 1'b0;
                         SREG[2] <= 1'b0;
                         SREG[3] <= 1'b0;
                     end
            4'b0110: begin
                         SREG[3:1] <= 3'b000;
                         reg_out = operandA|operandB;
                         SREG[0] = (reg_out === 0)?1:0;
                     end
            4'b0111: begin
                         SREG[3:1] <= 3'b000;
                         reg_out = operandA&operandB;
                         SREG[0] = (reg_out === 0)?1:0;
                     end
            default: begin
                         SREG <= 4'b0000;
                         reg_out <= reg_out;
                     end
        endcase
    end
endmodule

ALU-test.v
module testbench;

    wire[3:0] SREG;
    wire[7:0] reg_out;
    reg[7:0] A, B;
    reg[3:0] function_select_lines;

    initial begin
        $dumpfile("test-ALU-adder-sub.vcd");
        $dumpvars(0, testbench);
    end

    ALU uut (reg_out, SREG, function_select_lines, A, B);

    initial begin
        #1 A = 6; B = 9; function_select_lines = 1;
        #5 A = 3; B = 6; function_select_lines = 2;
        #5 B = 50;
        #5 A = 127; B = 125; function_select_lines = 1;
        #5 function_select_lines = 2;
        #5 B = -120;
        #5 A = 1; B = 2; function_select_lines = 3;
        #5 function_select_lines = 0;
        #5 A = 13; B = 85; function_select_lines = 6;
        #5 function_select_lines = 7;
        #5 $finish;
    end
endmodule

test-ALU-adder-sub.vcd
$date
	Fri Nov 29 09:15:14 2019
$end
$version
	Icarus Verilog
$end
$timescale
	1s
$end
$scope module testbench $end
$var wire 8 ! reg_out [7:0] $end
$var wire 4 " SREG [3:0] $end
$var reg 8 # A [7:0] $end
$var reg 8 $ B [7:0] $end
$var reg 4 % function_select_lines [3:0] $end
$scope module uut $end
$var wire 4 & function_select_lines [3:0] $end
$var wire 8 ' operandA [7:0] $end
$var wire 8 ( operandB [7:0] $end
$var reg 4 ) SREG [3:0] $end
$var reg 8 * reg_out [7:0] $end
$upscope $end
$upscope $end
$enddefinitions $end
#0
$dumpvars
bx *
bx )
bx (
bx '
bx &
bx %
bx $
bx #
bx "
bx !
$end
#1
b0 "
b0 )
b1111 !
b1111 *
b1 %
b1 &
b1001 $
b1001 (
b110 #
b110 '
#6
b110 "
b110 )
b11111101 !
b11111101 *
b10 %
b10 &
b110 $
b110 (
b11 #
b11 '
#11
b11010001 !
b11010001 *
b110010 $
b110010 (
#16
b1100 "
b1100 )
b11111100 !
b11111100 *
b1 %
b1 &
b1111101 $
b1111101 (
b1111111 #
b1111111 '
#21
b0 "
b0 )
b10 !
b10 *
b10 %
b10 &
#26
b1110 "
b1110 )
b11110111 !
b11110111 *
b10001000 $
b10001000 (
#31
b0 "
b0 )
b100 !
b100 *
b11 %
b11 &
b10 $
b10 (
b1 #
b1 '
#36
b0 %
b0 &
#41
b1011101 !
b1011101 *
b110 %
b110 &
b1010101 $
b1010101 (
b1101 #
b1101 '
#46
b101 !
b101 *
b111 %
b111 &
